mcdm/__init__.py
mcdm/electre.py
decisionpy-0.0.1.dist-info/LICENSE
decisionpy-0.0.1.dist-info/METADATA
decisionpy-0.0.1.dist-info/WHEEL
decisionpy-0.0.1.dist-info/top_level.txt
decisionpy-0.0.1.dist-info/RECORD
