Metadata-Version: 2.1
Name: decisionpy
Version: 0.0.1
Summary: For solving multi-criteria decision problem with python
Home-page: UNKNOWN
Author: Algın OKURSOY
Author-email: algin.okursoy@gmail.com
License: UNKNOWN
Platform: UNKNOWN
Classifier: Programming Language :: Python :: 3
Classifier: License :: OSI Approved :: MIT License
Classifier: Operating System :: OS Independent
Requires-Python: >=3.5
License-File: LICENSE
